[
  {
    "patch_version": "25.09",
    "gold_cost": 1600,
    "magic_pen_percent": 6
  },
  {
    "patch_version": "25.S1.1",
    "item_id": 3175,
    "item_name": "Spellslinger's Shoes",
    "components": [3020],
    "category": "Boots",
    "gold_cost": 1850,
    "movespeed_flat": 50,
    "magic_pen_flat": 18,
    "magic_pen_percent": 8,
    "buy_group": ["BOOTS"],
    "motd": "Hotfix: • Flat magic penetration reduced to 18 from 19. \n\n  • Percentage magic penetration reduced to 8% from 10%.",
    "passive_4_name": "REQUIREMENT",
    "passive_4": "Requires *Blessing of Noxus* and two Legendary-tier items equipped."
  }
]
